setup.py
ashwin_indian_state/__init__.py
ashwin_indian_state/asgi.py
ashwin_indian_state/settings.py
ashwin_indian_state/urls.py
ashwin_indian_state/wsgi.py
ashwin_indian_states.egg-info/PKG-INFO
ashwin_indian_states.egg-info/SOURCES.txt
ashwin_indian_states.egg-info/dependency_links.txt
ashwin_indian_states.egg-info/requires.txt
ashwin_indian_states.egg-info/top_level.txt
kst1/__init__.py
kst1/admin.py
kst1/apps.py
kst1/fields.py
kst1/forms.py
kst1/models.py
kst1/states.py
kst1/tests.py
kst1/views.py
kst1/migrations/__init__.py